MANIFEST.in
README.txt
setup.cfg
setup.py
collective/__init__.py
collective.atcassandrastorage.egg-info/PKG-INFO
collective.atcassandrastorage.egg-info/SOURCES.txt
collective.atcassandrastorage.egg-info/dependency_links.txt
collective.atcassandrastorage.egg-info/entry_points.txt
collective.atcassandrastorage.egg-info/namespace_packages.txt
collective.atcassandrastorage.egg-info/not-zip-safe
collective.atcassandrastorage.egg-info/paster_plugins.txt
collective.atcassandrastorage.egg-info/requires.txt
collective.atcassandrastorage.egg-info/top_level.txt
collective/atcassandrastorage/__init__.py
collective/atcassandrastorage/casa_mock.py
collective/atcassandrastorage/configure.zcml
collective/atcassandrastorage/db.py
collective/atcassandrastorage/interfaces.py
collective/atcassandrastorage/settings.py
collective/atcassandrastorage/storage.py
collective/atcassandrastorage/storage.rst
collective/atcassandrastorage/tests.py
collective/atcassandrastorage/profiles/default/registry.xml
docs/HISTORY.txt
docs/INSTALL.txt
docs/LICENSE.GPL
docs/LICENSE.txt