Metadata-Version: 1.0
Name: collective.atcassandrastorage
Version: 0.2
Summary: A AT field storage which stores values to a cassandra database
Home-page: http://github.com/seletz/collective.atcassandrastorage
Author: Stefan Eletzhofer
Author-email: stefan.eletzhofer@inquant.de
License: GPL
Keywords: plone archetype cassandra
Platform: UNKNOWN
Classifier: Framework :: Plone
Classifier: Programming Language :: Python
